Metadata-Version: 2.1
Name: pharma-datamatrix
Version: 1.4.5
Summary: Parse EU FMD compliant GS1 & PPN DataMatrix barcodes
Home-page: https://github.com/PinchofLogic/pharma_datamatrix
Author-email: saxenak02@gmail.com
License: UNKNOWN
Platform: UNKNOWN
